nepali_date_converter.py
nepali_date_converter-0.0.1.dist-info/LICENSE.txt
nepali_date_converter-0.0.1.dist-info/METADATA
nepali_date_converter-0.0.1.dist-info/WHEEL
nepali_date_converter-0.0.1.dist-info/top_level.txt
nepali_date_converter-0.0.1.dist-info/RECORD
