Metadata-Version: 2.1
Name: nepali_date_converter
Version: 0.0.1
Summary: NepaliDateConverter
Home-page: https://github.com/GKisi27/nepali_date_converter
Author: Gopal kisi
Author-email: gkisi2772@gmail.com
Keywords: python,tutorial,date_converter,bikram sambat,nepali date converter,nepali datetime,bs to ad converter,ad to bs converter,nepali datetime
Classifier: Development Status :: 3 - Alpha
Classifier: Intended Audience :: Developers
Classifier: Programming Language :: Python :: 3
Classifier: Operating System :: Unix
Classifier: Operating System :: MacOS :: MacOS X
Classifier: Operating System :: Microsoft :: Windows
Provides-Extra: dev
License-File: LICENSE.txt
